Metadata-Version: 1.0
Name: bacman
Version: 0.2
Summary: Easily take snapshots of Postgres and MySQL databases and upload to AWS S3.
Home-page: https://github.com/willandskill/bacman
Author: Will & Skill AB
Author-email: info@willandskill.se
License: BSD licence, see LICENCE.txt
Keywords: backup,database,mysql,postgres
Platform: UNKNOWN
